Metadata-Version: 1.1
Name: gfmd
Version: 0.1.3
Summary: GitHub Flavored Markdown
Home-page: https://github.com/kehao95/gfmd
Author: Hao Ke
Author-email: kehao95@gmail.com
License: UNKNOWN
Keywords: markdown
Platform: UNKNOWN
Classifier: Development Status :: 3 - Alpha
Classifier: Intended Audience :: Developers
Classifier: Topic :: Software Development :: Build Tools
Classifier: License :: OSI Approved :: MIT License
Classifier: Programming Language :: Python :: 2
Classifier: Programming Language :: Python :: 2.7
Classifier: Programming Language :: Python :: 3
Classifier: Programming Language :: Python :: 3.3
Classifier: Programming Language :: Python :: 3.4
Classifier: Programming Language :: Python :: 3.5
